pkg_scripts/__init__.py
pkg_scripts/db_management.py
pkg_scripts/environment_management.py
pkg_scripts/main.py
pkg_scripts/misc_functions.py
pkg_scripts/pkg_installation.py
pkg_scripts/pkg_uninstallation.py
pkg_scripts/pkg_updation.py
shopkeepr-1.1.4.dist-info/LICENSE
shopkeepr-1.1.4.dist-info/METADATA
shopkeepr-1.1.4.dist-info/WHEEL
shopkeepr-1.1.4.dist-info/entry_points.txt
shopkeepr-1.1.4.dist-info/top_level.txt
shopkeepr-1.1.4.dist-info/RECORD
