Metadata-Version: 2.1
Name: shopkeepr
Version: 1.1.4
Summary: A command line tool for project management. Made for Developers
Home-page: https://github.com/ayushpriya10/ShopKeepr
Author: Sameeran Bandishti, Ayush Priya
Author-email: shopkeepr3.6@gmail.com
License: UNKNOWN
Keywords: pip requirements automation
Platform: UNKNOWN
Classifier: Development Status :: 4 - Beta
Classifier: License :: OSI Approved :: MIT License 
Classifier: Programming Language :: Python :: 3.6
Requires-Dist: sqlalchemy
